tavily_tools/__init__.py
tavily_tools/cli/__init__.py
tavily_tools/cli/main.py
tavily_tools/config/__init__.py
tavily_tools/config/settings.py
tavily_tools/core/__init__.py
tavily_tools/core/formatter.py
tavily_tools/core/search.py
tavily_tools/utils/__init__.py
tavily_tools/utils/helpers.py
tavily_tools-0.1.0.dist-info/METADATA
tavily_tools-0.1.0.dist-info/WHEEL
tavily_tools-0.1.0.dist-info/entry_points.txt
tavily_tools-0.1.0.dist-info/licenses/LICENSE
tavily_tools-0.1.0.dist-info/RECORD
